discord/ext/sembed/__init__.py
sembed/__init__.py
sembed/sembed.py
sembed-1.1.3.dist-info/LICENSE
sembed-1.1.3.dist-info/METADATA
sembed-1.1.3.dist-info/WHEEL
sembed-1.1.3.dist-info/top_level.txt
sembed-1.1.3.dist-info/RECORD
