Metadata-Version: 2.1
Name: sembed
Version: 1.1.3
Summary: A wrapper of discord.Embed.
Home-page: https://github.com/sevenc-nanashi/sembed
Author: sevenc_nanashi
License: UNKNOWN
Project-URL: Bug Tracker, https://github.com/sevenc-nanashi/sembed/issues
Project-URL: Documentation, https://sembed.readthedocs.io
Platform: UNKNOWN
Classifier: Programming Language :: Python :: 3.8
Classifier: Programming Language :: Python :: 3.9
Classifier: License :: OSI Approved :: MIT License
Classifier: Operating System :: OS Independent
License-File: LICENSE
Requires-Dist: discord.py (<2.0.0,>=1.0.0)
